poetry_git_branch_plugin/__init__.py
poetry_git_branch_plugin/plugin.py
poetry_git_branch_plugin-0.1.0.dist-info/LICENSE
poetry_git_branch_plugin-0.1.0.dist-info/METADATA
poetry_git_branch_plugin-0.1.0.dist-info/WHEEL
poetry_git_branch_plugin-0.1.0.dist-info/entry_points.txt
poetry_git_branch_plugin-0.1.0.dist-info/RECORD
