Metadata-Version: 2.1
Name: poetry-git-branch-plugin
Version: 0.1.0
Summary: A poetry plugin to store the current git branch into environment variable when poetry runs any command.
Author: Francesc Font Clos
Author-email: fran@dribia.com
Requires-Python: >=3.10,<4.0
Classifier: Programming Language :: Python :: 3
Classifier: Programming Language :: Python :: 3.10
Classifier: Programming Language :: Python :: 3.11
Classifier: Programming Language :: Python :: 3.12
Requires-Dist: poetry (>=1.7.1,<2.0.0)
